{
  "id": "ecff0f01-8360-4077-9318-2c0c9bd4b522",
  "prevId": "00000000-0000-0000-0000-000000000000",
  "version": "7",
  "dialect": "postgresql",
  "tables": {
    "public.affiliateCommissions": {
      "name": "affiliateCommissions",
      "schema": "",
      "columns": {
        "id": {
          "name": "id",
          "type": "serial",
          "primaryKey": true,
          "notNull": true
        },
        "affiliateId": {
          "name": "affiliateId",
          "type": "integer",
          "primaryKey": false,
          "notNull": true
        },
        "referralId": {
          "name": "referralId",
          "type": "integer",
          "primaryKey": false,
          "notNull": true
        },
        "orderId": {
          "name": "orderId",
          "type": "varchar(255)",
          "primaryKey": false,
          "notNull": false
        },
        "type": {
          "name": "type",
          "type": "varchar(20)",
          "primaryKey": false,
          "notNull": true
        },
        "amount": {
          "name": "amount",
          "type": "integer",
          "primaryKey": false,
          "notNull": true
        },
        "status": {
          "name": "status",
          "type": "varchar(20)",
          "primaryKey": false,
          "notNull": true,
          "default": "'pending'"
        },
        "paidAt": {
          "name": "paidAt",
          "type": "timestamp",
          "primaryKey": false,
          "notNull": false
        },
        "createdAt": {
          "name": "createdAt",
          "type": "timestamp",
          "primaryKey": false,
          "notNull": true,
          "default": "now()"
        },
        "updatedAt": {
          "name": "updatedAt",
          "type": "timestamp",
          "primaryKey": false,
          "notNull": true,
          "default": "now()"
        }
      },
      "indexes": {},
      "foreignKeys": {},
      "compositePrimaryKeys": {},
      "uniqueConstraints": {},
      "policies": {},
      "checkConstraints": {},
      "isRLSEnabled": false
    },
    "public.affiliateReferrals": {
      "name": "affiliateReferrals",
      "schema": "",
      "columns": {
        "id": {
          "name": "id",
          "type": "serial",
          "primaryKey": true,
          "notNull": true
        },
        "affiliateId": {
          "name": "affiliateId",
          "type": "integer",
          "primaryKey": false,
          "notNull": true
        },
        "referredUserId": {
          "name": "referredUserId",
          "type": "integer",
          "primaryKey": false,
          "notNull": true
        },
        "status": {
          "name": "status",
          "type": "varchar(20)",
          "primaryKey": false,
          "notNull": true,
          "default": "'pending'"
        },
        "firstPurchaseAt": {
          "name": "firstPurchaseAt",
          "type": "timestamp",
          "primaryKey": false,
          "notNull": false
        },
        "lastPurchaseAt": {
          "name": "lastPurchaseAt",
          "type": "timestamp",
          "primaryKey": false,
          "notNull": false
        },
        "totalSpent": {
          "name": "totalSpent",
          "type": "integer",
          "primaryKey": false,
          "notNull": true,
          "default": 0
        },
        "totalCommission": {
          "name": "totalCommission",
          "type": "integer",
          "primaryKey": false,
          "notNull": true,
          "default": 0
        },
        "createdAt": {
          "name": "createdAt",
          "type": "timestamp",
          "primaryKey": false,
          "notNull": true,
          "default": "now()"
        },
        "updatedAt": {
          "name": "updatedAt",
          "type": "timestamp",
          "primaryKey": false,
          "notNull": true,
          "default": "now()"
        }
      },
      "indexes": {},
      "foreignKeys": {},
      "compositePrimaryKeys": {},
      "uniqueConstraints": {},
      "policies": {},
      "checkConstraints": {},
      "isRLSEnabled": false
    },
    "public.affiliates": {
      "name": "affiliates",
      "schema": "",
      "columns": {
        "id": {
          "name": "id",
          "type": "serial",
          "primaryKey": true,
          "notNull": true
        },
        "userId": {
          "name": "userId",
          "type": "integer",
          "primaryKey": false,
          "notNull": true
        },
        "code": {
          "name": "code",
          "type": "varchar(32)",
          "primaryKey": false,
          "notNull": true
        },
        "status": {
          "name": "status",
          "type": "varchar(20)",
          "primaryKey": false,
          "notNull": true,
          "default": "'pending'"
        },
        "tier": {
          "name": "tier",
          "type": "varchar(20)",
          "primaryKey": false,
          "notNull": true,
          "default": "'standard'"
        },
        "commissionRate": {
          "name": "commissionRate",
          "type": "integer",
          "primaryKey": false,
          "notNull": true,
          "default": 30
        },
        "recurringCommissionRate": {
          "name": "recurringCommissionRate",
          "type": "integer",
          "primaryKey": false,
          "notNull": true,
          "default": 10
        },
        "totalEarnings": {
          "name": "totalEarnings",
          "type": "integer",
          "primaryKey": false,
          "notNull": true,
          "default": 0
        },
        "pendingEarnings": {
          "name": "pendingEarnings",
          "type": "integer",
          "primaryKey": false,
          "notNull": true,
          "default": 0
        },
        "paidEarnings": {
          "name": "paidEarnings",
          "type": "integer",
          "primaryKey": false,
          "notNull": true,
          "default": 0
        },
        "totalReferrals": {
          "name": "totalReferrals",
          "type": "integer",
          "primaryKey": false,
          "notNull": true,
          "default": 0
        },
        "activeReferrals": {
          "name": "activeReferrals",
          "type": "integer",
          "primaryKey": false,
          "notNull": true,
          "default": 0
        },
        "pixKey": {
          "name": "pixKey",
          "type": "varchar(255)",
          "primaryKey": false,
          "notNull": false
        },
        "lastPayoutAt": {
          "name": "lastPayoutAt",
          "type": "timestamp",
          "primaryKey": false,
          "notNull": false
        },
        "createdAt": {
          "name": "createdAt",
          "type": "timestamp",
          "primaryKey": false,
          "notNull": true,
          "default": "now()"
        },
        "updatedAt": {
          "name": "updatedAt",
          "type": "timestamp",
          "primaryKey": false,
          "notNull": true,
          "default": "now()"
        }
      },
      "indexes": {},
      "foreignKeys": {},
      "compositePrimaryKeys": {},
      "uniqueConstraints": {
        "affiliates_userId_unique": {
          "name": "affiliates_userId_unique",
          "nullsNotDistinct": false,
          "columns": [
            "userId"
          ]
        },
        "affiliates_code_unique": {
          "name": "affiliates_code_unique",
          "nullsNotDistinct": false,
          "columns": [
            "code"
          ]
        }
      },
      "policies": {},
      "checkConstraints": {},
      "isRLSEnabled": false
    },
    "public.creditPurchases": {
      "name": "creditPurchases",
      "schema": "",
      "columns": {
        "id": {
          "name": "id",
          "type": "serial",
          "primaryKey": true,
          "notNull": true
        },
        "userId": {
          "name": "userId",
          "type": "integer",
          "primaryKey": false,
          "notNull": true
        },
        "credits": {
          "name": "credits",
          "type": "integer",
          "primaryKey": false,
          "notNull": true
        },
        "amount": {
          "name": "amount",
          "type": "integer",
          "primaryKey": false,
          "notNull": true
        },
        "paymentMethod": {
          "name": "paymentMethod",
          "type": "varchar(50)",
          "primaryKey": false,
          "notNull": false
        },
        "stripePaymentIntentId": {
          "name": "stripePaymentIntentId",
          "type": "varchar(255)",
          "primaryKey": false,
          "notNull": false
        },
        "status": {
          "name": "status",
          "type": "varchar(20)",
          "primaryKey": false,
          "notNull": true,
          "default": "'pending'"
        },
        "createdAt": {
          "name": "createdAt",
          "type": "timestamp",
          "primaryKey": false,
          "notNull": true,
          "default": "now()"
        },
        "updatedAt": {
          "name": "updatedAt",
          "type": "timestamp",
          "primaryKey": false,
          "notNull": true,
          "default": "now()"
        }
      },
      "indexes": {},
      "foreignKeys": {},
      "compositePrimaryKeys": {},
      "uniqueConstraints": {},
      "policies": {},
      "checkConstraints": {},
      "isRLSEnabled": false
    },
    "public.loyaltyPoints": {
      "name": "loyaltyPoints",
      "schema": "",
      "columns": {
        "id": {
          "name": "id",
          "type": "serial",
          "primaryKey": true,
          "notNull": true
        },
        "userId": {
          "name": "userId",
          "type": "integer",
          "primaryKey": false,
          "notNull": true
        },
        "points": {
          "name": "points",
          "type": "integer",
          "primaryKey": false,
          "notNull": true
        },
        "type": {
          "name": "type",
          "type": "varchar(20)",
          "primaryKey": false,
          "notNull": true
        },
        "reason": {
          "name": "reason",
          "type": "varchar(255)",
          "primaryKey": false,
          "notNull": true
        },
        "referenceId": {
          "name": "referenceId",
          "type": "integer",
          "primaryKey": false,
          "notNull": false
        },
        "expiresAt": {
          "name": "expiresAt",
          "type": "timestamp",
          "primaryKey": false,
          "notNull": false
        },
        "createdAt": {
          "name": "createdAt",
          "type": "timestamp",
          "primaryKey": false,
          "notNull": true,
          "default": "now()"
        }
      },
      "indexes": {},
      "foreignKeys": {},
      "compositePrimaryKeys": {},
      "uniqueConstraints": {},
      "policies": {},
      "checkConstraints": {},
      "isRLSEnabled": false
    },
    "public.memories": {
      "name": "memories",
      "schema": "",
      "columns": {
        "id": {
          "name": "id",
          "type": "serial",
          "primaryKey": true,
          "notNull": true
        },
        "userId": {
          "name": "userId",
          "type": "integer",
          "primaryKey": false,
          "notNull": true
        },
        "title": {
          "name": "title",
          "type": "varchar(255)",
          "primaryKey": false,
          "notNull": true
        },
        "story": {
          "name": "story",
          "type": "text",
          "primaryKey": false,
          "notNull": true
        },
        "format": {
          "name": "format",
          "type": "varchar(20)",
          "primaryKey": false,
          "notNull": true
        },
        "status": {
          "name": "status",
          "type": "varchar(20)",
          "primaryKey": false,
          "notNull": true,
          "default": "'processing'"
        },
        "isPublic": {
          "name": "isPublic",
          "type": "boolean",
          "primaryKey": false,
          "notNull": true,
          "default": false
        },
        "videoUrl": {
          "name": "videoUrl",
          "type": "text",
          "primaryKey": false,
          "notNull": false
        },
        "musicUrl": {
          "name": "musicUrl",
          "type": "text",
          "primaryKey": false,
          "notNull": false
        },
        "bookUrl": {
          "name": "bookUrl",
          "type": "text",
          "primaryKey": false,
          "notNull": false
        },
        "podcastUrl": {
          "name": "podcastUrl",
          "type": "text",
          "primaryKey": false,
          "notNull": false
        },
        "animationUrl": {
          "name": "animationUrl",
          "type": "text",
          "primaryKey": false,
          "notNull": false
        },
        "nftUrl": {
          "name": "nftUrl",
          "type": "text",
          "primaryKey": false,
          "notNull": false
        },
        "thumbnailUrl": {
          "name": "thumbnailUrl",
          "type": "text",
          "primaryKey": false,
          "notNull": false
        },
        "views": {
          "name": "views",
          "type": "integer",
          "primaryKey": false,
          "notNull": true,
          "default": 0
        },
        "likes": {
          "name": "likes",
          "type": "integer",
          "primaryKey": false,
          "notNull": true,
          "default": 0
        },
        "shares": {
          "name": "shares",
          "type": "integer",
          "primaryKey": false,
          "notNull": true,
          "default": 0
        },
        "createdAt": {
          "name": "createdAt",
          "type": "timestamp",
          "primaryKey": false,
          "notNull": true,
          "default": "now()"
        },
        "updatedAt": {
          "name": "updatedAt",
          "type": "timestamp",
          "primaryKey": false,
          "notNull": true,
          "default": "now()"
        }
      },
      "indexes": {},
      "foreignKeys": {},
      "compositePrimaryKeys": {},
      "uniqueConstraints": {},
      "policies": {},
      "checkConstraints": {},
      "isRLSEnabled": false
    },
    "public.notificationPreferences": {
      "name": "notificationPreferences",
      "schema": "",
      "columns": {
        "id": {
          "name": "id",
          "type": "serial",
          "primaryKey": true,
          "notNull": true
        },
        "userId": {
          "name": "userId",
          "type": "integer",
          "primaryKey": false,
          "notNull": true
        },
        "emailMemoryCompleted": {
          "name": "emailMemoryCompleted",
          "type": "boolean",
          "primaryKey": false,
          "notNull": true,
          "default": true
        },
        "emailNewLike": {
          "name": "emailNewLike",
          "type": "boolean",
          "primaryKey": false,
          "notNull": true,
          "default": false
        },
        "emailNewComment": {
          "name": "emailNewComment",
          "type": "boolean",
          "primaryKey": false,
          "notNull": true,
          "default": true
        },
        "emailPayment": {
          "name": "emailPayment",
          "type": "boolean",
          "primaryKey": false,
          "notNull": true,
          "default": true
        },
        "pushMemoryCompleted": {
          "name": "pushMemoryCompleted",
          "type": "boolean",
          "primaryKey": false,
          "notNull": true,
          "default": true
        },
        "pushNewLike": {
          "name": "pushNewLike",
          "type": "boolean",
          "primaryKey": false,
          "notNull": true,
          "default": false
        },
        "pushNewComment": {
          "name": "pushNewComment",
          "type": "boolean",
          "primaryKey": false,
          "notNull": true,
          "default": true
        },
        "createdAt": {
          "name": "createdAt",
          "type": "timestamp",
          "primaryKey": false,
          "notNull": true,
          "default": "now()"
        },
        "updatedAt": {
          "name": "updatedAt",
          "type": "timestamp",
          "primaryKey": false,
          "notNull": true,
          "default": "now()"
        }
      },
      "indexes": {},
      "foreignKeys": {},
      "compositePrimaryKeys": {},
      "uniqueConstraints": {
        "notificationPreferences_userId_unique": {
          "name": "notificationPreferences_userId_unique",
          "nullsNotDistinct": false,
          "columns": [
            "userId"
          ]
        }
      },
      "policies": {},
      "checkConstraints": {},
      "isRLSEnabled": false
    },
    "public.notifications": {
      "name": "notifications",
      "schema": "",
      "columns": {
        "id": {
          "name": "id",
          "type": "serial",
          "primaryKey": true,
          "notNull": true
        },
        "userId": {
          "name": "userId",
          "type": "integer",
          "primaryKey": false,
          "notNull": true
        },
        "type": {
          "name": "type",
          "type": "varchar(50)",
          "primaryKey": false,
          "notNull": true
        },
        "title": {
          "name": "title",
          "type": "varchar(255)",
          "primaryKey": false,
          "notNull": true
        },
        "message": {
          "name": "message",
          "type": "text",
          "primaryKey": false,
          "notNull": true
        },
        "link": {
          "name": "link",
          "type": "varchar(500)",
          "primaryKey": false,
          "notNull": false
        },
        "imageUrl": {
          "name": "imageUrl",
          "type": "text",
          "primaryKey": false,
          "notNull": false
        },
        "actionUrl": {
          "name": "actionUrl",
          "type": "varchar(500)",
          "primaryKey": false,
          "notNull": false
        },
        "actionLabel": {
          "name": "actionLabel",
          "type": "varchar(100)",
          "primaryKey": false,
          "notNull": false
        },
        "priority": {
          "name": "priority",
          "type": "varchar(20)",
          "primaryKey": false,
          "notNull": true,
          "default": "'normal'"
        },
        "isRead": {
          "name": "isRead",
          "type": "boolean",
          "primaryKey": false,
          "notNull": true,
          "default": false
        },
        "readAt": {
          "name": "readAt",
          "type": "timestamp",
          "primaryKey": false,
          "notNull": false
        },
        "scheduledFor": {
          "name": "scheduledFor",
          "type": "timestamp",
          "primaryKey": false,
          "notNull": false
        },
        "sentAt": {
          "name": "sentAt",
          "type": "timestamp",
          "primaryKey": false,
          "notNull": false
        },
        "emailSent": {
          "name": "emailSent",
          "type": "boolean",
          "primaryKey": false,
          "notNull": true,
          "default": false
        },
        "emailSentAt": {
          "name": "emailSentAt",
          "type": "timestamp",
          "primaryKey": false,
          "notNull": false
        },
        "createdAt": {
          "name": "createdAt",
          "type": "timestamp",
          "primaryKey": false,
          "notNull": true,
          "default": "now()"
        }
      },
      "indexes": {},
      "foreignKeys": {},
      "compositePrimaryKeys": {},
      "uniqueConstraints": {},
      "policies": {},
      "checkConstraints": {},
      "isRLSEnabled": false
    },
    "public.premiumTemplates": {
      "name": "premiumTemplates",
      "schema": "",
      "columns": {
        "id": {
          "name": "id",
          "type": "serial",
          "primaryKey": true,
          "notNull": true
        },
        "name": {
          "name": "name",
          "type": "varchar(255)",
          "primaryKey": false,
          "notNull": true
        },
        "description": {
          "name": "description",
          "type": "text",
          "primaryKey": false,
          "notNull": false
        },
        "category": {
          "name": "category",
          "type": "varchar(50)",
          "primaryKey": false,
          "notNull": true
        },
        "price": {
          "name": "price",
          "type": "integer",
          "primaryKey": false,
          "notNull": true
        },
        "thumbnailUrl": {
          "name": "thumbnailUrl",
          "type": "text",
          "primaryKey": false,
          "notNull": false
        },
        "previewUrl": {
          "name": "previewUrl",
          "type": "text",
          "primaryKey": false,
          "notNull": false
        },
        "config": {
          "name": "config",
          "type": "text",
          "primaryKey": false,
          "notNull": false
        },
        "isActive": {
          "name": "isActive",
          "type": "boolean",
          "primaryKey": false,
          "notNull": true,
          "default": true
        },
        "salesCount": {
          "name": "salesCount",
          "type": "integer",
          "primaryKey": false,
          "notNull": true,
          "default": 0
        },
        "createdAt": {
          "name": "createdAt",
          "type": "timestamp",
          "primaryKey": false,
          "notNull": true,
          "default": "now()"
        },
        "updatedAt": {
          "name": "updatedAt",
          "type": "timestamp",
          "primaryKey": false,
          "notNull": true,
          "default": "now()"
        }
      },
      "indexes": {},
      "foreignKeys": {},
      "compositePrimaryKeys": {},
      "uniqueConstraints": {},
      "policies": {},
      "checkConstraints": {},
      "isRLSEnabled": false
    },
    "public.referrals": {
      "name": "referrals",
      "schema": "",
      "columns": {
        "id": {
          "name": "id",
          "type": "serial",
          "primaryKey": true,
          "notNull": true
        },
        "referrerId": {
          "name": "referrerId",
          "type": "integer",
          "primaryKey": false,
          "notNull": true
        },
        "referredUserId": {
          "name": "referredUserId",
          "type": "integer",
          "primaryKey": false,
          "notNull": true
        },
        "code": {
          "name": "code",
          "type": "varchar(32)",
          "primaryKey": false,
          "notNull": true
        },
        "status": {
          "name": "status",
          "type": "varchar(20)",
          "primaryKey": false,
          "notNull": true,
          "default": "'pending'"
        },
        "rewardType": {
          "name": "rewardType",
          "type": "varchar(20)",
          "primaryKey": false,
          "notNull": false
        },
        "rewardAmount": {
          "name": "rewardAmount",
          "type": "integer",
          "primaryKey": false,
          "notNull": false
        },
        "rewardedAt": {
          "name": "rewardedAt",
          "type": "timestamp",
          "primaryKey": false,
          "notNull": false
        },
        "createdAt": {
          "name": "createdAt",
          "type": "timestamp",
          "primaryKey": false,
          "notNull": true,
          "default": "now()"
        },
        "updatedAt": {
          "name": "updatedAt",
          "type": "timestamp",
          "primaryKey": false,
          "notNull": true,
          "default": "now()"
        }
      },
      "indexes": {},
      "foreignKeys": {},
      "compositePrimaryKeys": {},
      "uniqueConstraints": {},
      "policies": {},
      "checkConstraints": {},
      "isRLSEnabled": false
    },
    "public.templatePurchases": {
      "name": "templatePurchases",
      "schema": "",
      "columns": {
        "id": {
          "name": "id",
          "type": "serial",
          "primaryKey": true,
          "notNull": true
        },
        "userId": {
          "name": "userId",
          "type": "integer",
          "primaryKey": false,
          "notNull": true
        },
        "templateId": {
          "name": "templateId",
          "type": "integer",
          "primaryKey": false,
          "notNull": true
        },
        "amount": {
          "name": "amount",
          "type": "integer",
          "primaryKey": false,
          "notNull": true
        },
        "stripePaymentIntentId": {
          "name": "stripePaymentIntentId",
          "type": "varchar(255)",
          "primaryKey": false,
          "notNull": false
        },
        "createdAt": {
          "name": "createdAt",
          "type": "timestamp",
          "primaryKey": false,
          "notNull": true,
          "default": "now()"
        }
      },
      "indexes": {},
      "foreignKeys": {},
      "compositePrimaryKeys": {},
      "uniqueConstraints": {},
      "policies": {},
      "checkConstraints": {},
      "isRLSEnabled": false
    },
    "public.users": {
      "name": "users",
      "schema": "",
      "columns": {
        "id": {
          "name": "id",
          "type": "serial",
          "primaryKey": true,
          "notNull": true
        },
        "openId": {
          "name": "openId",
          "type": "varchar(64)",
          "primaryKey": false,
          "notNull": true
        },
        "name": {
          "name": "name",
          "type": "text",
          "primaryKey": false,
          "notNull": false
        },
        "email": {
          "name": "email",
          "type": "varchar(320)",
          "primaryKey": false,
          "notNull": false
        },
        "password": {
          "name": "password",
          "type": "varchar(255)",
          "primaryKey": false,
          "notNull": false
        },
        "loginMethod": {
          "name": "loginMethod",
          "type": "varchar(64)",
          "primaryKey": false,
          "notNull": false
        },
        "role": {
          "name": "role",
          "type": "varchar(20)",
          "primaryKey": false,
          "notNull": true,
          "default": "'user'"
        },
        "plan": {
          "name": "plan",
          "type": "varchar(20)",
          "primaryKey": false,
          "notNull": true,
          "default": "'free'"
        },
        "planInterval": {
          "name": "planInterval",
          "type": "varchar(20)",
          "primaryKey": false,
          "notNull": false,
          "default": "'monthly'"
        },
        "subscriptionId": {
          "name": "subscriptionId",
          "type": "varchar(255)",
          "primaryKey": false,
          "notNull": false
        },
        "subscriptionStatus": {
          "name": "subscriptionStatus",
          "type": "varchar(20)",
          "primaryKey": false,
          "notNull": false
        },
        "currentPeriodEnd": {
          "name": "currentPeriodEnd",
          "type": "timestamp",
          "primaryKey": false,
          "notNull": false
        },
        "creditsRemaining": {
          "name": "creditsRemaining",
          "type": "integer",
          "primaryKey": false,
          "notNull": true,
          "default": 3
        },
        "createdAt": {
          "name": "createdAt",
          "type": "timestamp",
          "primaryKey": false,
          "notNull": true,
          "default": "now()"
        },
        "updatedAt": {
          "name": "updatedAt",
          "type": "timestamp",
          "primaryKey": false,
          "notNull": true,
          "default": "now()"
        },
        "lastSignedIn": {
          "name": "lastSignedIn",
          "type": "timestamp",
          "primaryKey": false,
          "notNull": true,
          "default": "now()"
        }
      },
      "indexes": {},
      "foreignKeys": {},
      "compositePrimaryKeys": {},
      "uniqueConstraints": {
        "users_openId_unique": {
          "name": "users_openId_unique",
          "nullsNotDistinct": false,
          "columns": [
            "openId"
          ]
        }
      },
      "policies": {},
      "checkConstraints": {},
      "isRLSEnabled": false
    }
  },
  "enums": {},
  "schemas": {},
  "sequences": {},
  "roles": {},
  "policies": {},
  "views": {},
  "_meta": {
    "columns": {},
    "schemas": {},
    "tables": {}
  }
}